{
    "passport": [
        {
            "expiryDate": "2030-01-01",
            "documentNumber": "321654987"
        }
    ],
    "name": [
        {
            "nameParts": [
                {
                    "type": "GivenName",
                    "value": "Kenneth"
                },
                {
                    "type": "FamilyName",
                    "value": "Decerqueira"
                }
            ]
        }
    ],
    "birthDate": [
        {
            "value": "1964-11-07"
        }
    ]
}